trueface_utils/__init__.py
trueface_utils/memsql.py
trueface_utils/server.py
trueface_utils/streaming.py
trueface_utils/tracking.py
trueface_utils/utils.py
trueface_utils-0.0.4.dist-info/DESCRIPTION.rst
trueface_utils-0.0.4.dist-info/METADATA
trueface_utils-0.0.4.dist-info/RECORD
trueface_utils-0.0.4.dist-info/WHEEL
trueface_utils-0.0.4.dist-info/metadata.json
trueface_utils-0.0.4.dist-info/top_level.txt
