Metadata-Version: 2.0
Name: trueface-utils
Version: 0.0.4
Summary: Trueface utils package
Home-page: https://docs.trueface.ai
Author: Trueface
Author-email: support@trueface.ai
License: UNKNOWN
Project-URL: Bug Tracker, https://support.trueface.ai
Platform: UNKNOWN
Classifier: Programming Language :: Python :: 3
